exioml/__init__.py
exioml/__main__.py
exioml/cli.py
exioml/data_io.py
exioml/datasets.py
exioml/factors.py
exioml/logging_utils.py
exioml/preprocessing.py
exioml/training.py
exioml-0.2.1.dist-info/licenses/LICENSE
exioml-0.2.1.dist-info/METADATA
exioml-0.2.1.dist-info/WHEEL
exioml-0.2.1.dist-info/entry_points.txt
exioml-0.2.1.dist-info/top_level.txt
exioml-0.2.1.dist-info/RECORD
