Metadata-Version: 2.4
Name: exioml
Version: 0.2.1
Summary: Exiobase-derived emission factor loader with caching and CLI utilities
Author-email: ExioML <team@exioml.dev>
License:                                  Apache License
Project-URL: Homepage, https://github.com/exioml/exioml
Project-URL: Bug Tracker, https://github.com/exioml/exioml/issues
Keywords: exiobase,emissions,sustainability,scope3,mrio
Classifier: Programming Language :: Python :: 3
Classifier: License :: OSI Approved :: MIT License
Classifier: Operating System :: OS Independent
Classifier: Intended Audience :: Science/Research
Classifier: Topic :: Scientific/Engineering :: Information Analysis
Requires-Python: >=3.9
License-File: LICENSE
Requires-Dist: pandas>=2.0
Requires-Dist: numpy>=1.24
Requires-Dist: requests>=2.31
Requires-Dist: fsspec>=2023.9.0
Requires-Dist: scikit-learn>=1.3
Provides-Extra: polars
Requires-Dist: polars>=0.20; extra == "polars"
Provides-Extra: arrow
Requires-Dist: pyarrow>=12.0; extra == "arrow"
Dynamic: license-file
